DrcomExecutor/__init__.py
DrcomExecutor/__main__.py
DrcomExecutor/core.py
DrcomExecutor/info.py
DrcomExecutor/utils.py
DrcomExecutor/version.py
DrcomExecutor/config/__init__.py
DrcomExecutor/config/config.py
DrcomExecutor/config/config_default.yaml
cqu_de-0.3.5.dist-info/LICENSE
cqu_de-0.3.5.dist-info/METADATA
cqu_de-0.3.5.dist-info/WHEEL
cqu_de-0.3.5.dist-info/entry_points.txt
cqu_de-0.3.5.dist-info/top_level.txt
cqu_de-0.3.5.dist-info/RECORD
