Metadata-Version: 2.1
Name: cqu-de
Version: 0.3.5
Summary: 基于 Python3 的第三方重庆大学Dr.COM登录器
Home-page: https://github.com/CQU-AI/DrcomExecutor
Author: CQU-AI
Author-email: peter@mail.loopy.tech
License: GPL License
Platform: all
Requires-Python: >=3.6
Requires-Dist: beautifulsoup4 (>=4.9.1)
Requires-Dist: PyYAML (>=5.3.1)
Requires-Dist: requests (>=2.24.0)
